{"frameRate":30,"name":"DBP_Animation","version":"5.5","compatibleVersion":"5.5","armature":[{"type":"Armature","frameRate":30,"name":"Armature","aabb":{"x":-24.93,"y":-61.57,"width":50.5,"height":113.86},"bone":[{"name":"root"},{"length":56,"name":"Torso","parent":"root","transform":{"x":-0.1024,"y":28.5,"skX":-90,"skY":-90}},{"length":27,"name":"Arm_L","parent":"Torso","transform":{"x":51.5,"y":13.2497,"skX":133.0746,"skY":133.0746}},{"length":27,"name":"Arm_R","parent":"Torso","transform":{"x":51.5,"y":-13.25,"skX":-137.6486,"skY":-137.6486}},{"length":3,"name":"Head","parent":"Torso","transform":{"x":54.8017,"y":-0.25,"skX":-0.051,"skY":-0.051}},{"length":27,"name":"Leg_R","parent":"Torso","transform":{"x":3.24,"y":-11.4,"skX":180,"skY":180}},{"length":26,"name":"Leg_L","parent":"Torso","transform":{"x":3.2435,"y":11.4,"skX":180,"skY":180}}],"slot":[{"name":"Head","parent":"Head"},{"name":"Leg_R","parent":"Leg_R"},{"name":"Leg_L","parent":"Leg_L"},{"name":"Arm_R","parent":"Arm_R"},{"name":"Arm_L","parent":"Arm_L"},{"name":"FaceScared","parent":"Head"},{"name":"Torso","parent":"Torso"},{"displayIndex":-1,"name":"FaceDead","parent":"Head"},{"displayIndex":-1,"name":"FaceHappy","parent":"Head"},{"displayIndex":-1,"name":"FaceStruggling","parent":"Head"}],"skin":[{"slot":[{"name":"Arm_R","display":[{"name":"Arm","transform":{"x":10.47,"y":0.04,"skX":-89.86,"skY":-89.86}}]},{"name":"Arm_L","display":[{"name":"Arm","transform":{"x":10.65,"y":-0.21,"skX":-89.81,"skY":-89.81}}]},{"name":"FaceScared","display":[{"name":"FaceScared","transform":{"x":16.11,"y":0.35,"skX":90,"skY":90}}]},{"name":"Torso","display":[{"name":"Torso","transform":{"x":28.48,"skX":90,"skY":90}}]},{"name":"FaceDead","display":[{"name":"FaceDead","transform":{"x":15.89,"y":0.01,"skX":90.05,"skY":90.05}}]},{"name":"FaceHappy","display":[{"name":"FaceHappy","transform":{"x":16.11,"y":0.01,"skX":90.05,"skY":90.05}}]},{"name":"Head","display":[{"name":"Head","transform":{"x":17.26,"y":0.35,"skX":90,"skY":90}}]},{"name":"Leg_R","display":[{"name":"Leg","transform":{"x":12.03,"y":-0.15,"skX":-90,"skY":-90}}]},{"name":"FaceStruggling","display":[{"name":"FaceStruggling","transform":{"x":16.56,"y":0.01,"skX":90.05,"skY":90.05}}]},{"name":"Leg_L","display":[{"name":"Leg","transform":{"x":11.84,"y":0.25,"skX":-89.5,"skY":-89.5}}]}]}],"animation":[{"duration":30,"playTimes":0,"name":"Idle","bone":[{"name":"Arm_L","rotateFrame":[{"duration":15,"tweenEasing":0},{"duration":15,"tweenEasing":0,"rotate":-93.07},{"duration":0,"rotate":6.93}]},{"name":"Arm_R","rotateFrame":[{"duration":15,"tweenEasing":0},{"duration":15,"tweenEasing":0,"rotate":97.65},{"duration":0,"rotate":-2.35}]}]},{"duration":15,"playTimes":0,"name":"Struggle","bone":[{"name":"Arm_L","rotateFrame":[{"duration":4,"tweenEasing":0,"rotate":-50.07},{"duration":7,"tweenEasing":0,"rotate":-100.07},{"duration":4,"tweenEasing":0,"rotate":-0.07},{"duration":0,"rotate":-50.07}]},{"name":"Arm_R","rotateFrame":[{"duration":8,"tweenEasing":0},{"duration":7,"tweenEasing":0,"rotate":100.65},{"duration":0}]},{"name":"Leg_R","rotateFrame":[{"duration":4,"tweenEasing":0,"rotate":20},{"duration":7,"tweenEasing":0,"rotate":40},{"duration":4,"tweenEasing":0},{"duration":0,"rotate":20}]},{"name":"Leg_L","rotateFrame":[{"duration":8,"tweenEasing":0},{"duration":7,"tweenEasing":0,"rotate":-40},{"duration":0}]}],"slot":[{"name":"FaceScared","displayFrame":[{"duration":15,"value":-1}]},{"name":"FaceStruggling","displayFrame":[{"duration":15}]}]},{"duration":30,"playTimes":0,"name":"Happy","bone":[{"name":"Torso","translateFrame":[{"duration":15,"curve":[0,0,0.5,1],"y":-0.27},{"duration":15,"curve":[0.22,0,0.44,0.1936,0.617408,0.410432,0.8432,0.6864,1,1],"y":-13.06},{"duration":0,"y":-0.27}]},{"name":"Arm_L","rotateFrame":[{"duration":15,"tweenEasing":0},{"duration":15,"tweenEasing":0,"rotate":-68.07},{"duration":0}]},{"name":"Arm_R","rotateFrame":[{"duration":16,"tweenEasing":0},{"duration":14,"tweenEasing":0,"rotate":72.65},{"duration":0}]},{"name":"Leg_R","rotateFrame":[{"duration":15,"tweenEasing":0},{"duration":15,"tweenEasing":0,"rotate":30},{"duration":0}]},{"name":"Leg_L","rotateFrame":[{"duration":15,"tweenEasing":0},{"duration":15,"tweenEasing":0,"rotate":-30},{"duration":0}]}],"slot":[{"name":"FaceScared","displayFrame":[{"duration":30,"value":-1}]},{"name":"FaceHappy","displayFrame":[{"duration":30}]}]},{"duration":0,"playTimes":0,"name":"Dead","slot":[{"name":"FaceScared","displayFrame":[{"duration":0,"value":-1}]},{"name":"FaceDead","displayFrame":[{"duration":0}]}]}],"defaultActions":[{"gotoAndPlay":"Idle"}]}]}